<?xml version="1.0" encoding="UTF-8"?>
<!DOCTYPE plist PUBLIC "-//Apple//DTD PLIST 1.0//EN" "http://www.apple.com/DTDs/PropertyList-1.0.dtd"/>

<plist version="1.0">
    <dict>
        <key>ROOT</key>
        <array>
            <dict>
                <key>id</key>
                <string>97</string>
                <key>children</key>
                <array>
                    <string>6032</string>
                    <string>6111</string>
                    <string>6113</string>
                    <string>6115</string>
                    <string>6117</string>
                    <string>6119</string>
                    <string>6121</string>
                    <string>6123</string>
                    <string>6125</string>
                    <string>6127</string>
                    <string>6129</string>
                    <string>6131</string>
                    <string>6133</string>
                    <string>6135</string>
                    <string>6137</string>
                    <string>6139</string>
                    <string>6141</string>
                    <string>6143</string>
                    <string>7630</string>
                    <string>10131</string>
                </array>
                <key>childLinkers</key>
                <array/>
            </dict>
            <dict>
                <key>id</key>
                <string>98</string>
                <key>children</key>
                <array>
                    <string>6228</string>
                    <string>6276</string>
                    <string>6278</string>
                    <string>6280</string>
                    <string>6309</string>
                    <string>6311</string>
                    <string>6313</string>
                    <string>6315</string>
                    <string>6325</string>
                    <string>6372</string>
                    <string>6397</string>
                    <string>6399</string>
                    <string>6401</string>
                    <string>6407</string>
                    <string>6409</string>
                    <string>6411</string>
                    <string>6413</string>
                    <string>6473</string>
                    <string>6478</string>
                    <string>6480</string>
                    <string>6482</string>
                    <string>6486</string>
                    <string>6488</string>
                    <string>6490</string>
                    <string>6499</string>
                    <string>6509</string>
                    <string>10895</string>
                    <string>11349</string>
                    <string>11351</string>
                    <string>11403</string>
                    <string>11405</string>
                    <string>12436</string>
                    <string>12438</string>
                    <string>12442</string>
                    <string>13970</string>
                    <string>13973</string>
                    <string>13977</string>
                    <string>13984</string>
                    <string>13987</string>
                    <string>13992</string>
                    <string>14147</string>
                    <string>14161</string>
                    <string>14175</string>
                    <string>14182</string>
                    <string>14184</string>
                    <string>14186</string>
                    <string>14189</string>
                    <string>14200</string>
                    <string>14208</string>
                    <string>14210</string>
                    <string>14212</string>
                    <string>14214</string>
                    <string>14263</string>
                </array>
                <key>childLinkers</key>
                <array/>
            </dict>
            <dict>
                <key>id</key>
                <string>151</string>
                <key>children</key>
                <array>
                    <string>6551</string>
                    <string>6553</string>
                    <string>6555</string>
                    <string>6557</string>
                    <string>6561</string>
                    <string>6563</string>
                    <string>6565</string>
                    <string>6567</string>
                    <string>6569</string>
                    <string>6571</string>
                    <string>6573</string>
                    <string>6575</string>
                    <string>6577</string>
                    <string>6579</string>
                    <string>6581</string>
                    <string>6583</string>
                    <string>6585</string>
                    <string>6591</string>
                    <string>6595</string>
                    <string>6631</string>
                    <string>6633</string>
                    <string>6635</string>
                    <string>6639</string>
                    <string>6641</string>
                    <string>6646</string>
                    <string>6653</string>
                    <string>6655</string>
                    <string>6659</string>
                    <string>6661</string>
                    <string>7424</string>
                    <string>7825</string>
                    <string>12483</string>
                    <string>12525</string>
                    <string>14225</string>
                    <string>14227</string>
                    <string>14229</string>
                    <string>14232</string>
                    <string>14234</string>
                    <string>14248</string>
                    <string>14283</string>
                    <string>14285</string>
                    <string>14287</string>
                    <string>14296</string>
                    <string>14299</string>
                    <string>14301</string>
                    <string>14303</string>
                    <string>14305</string>
                    <string>14307</string>
                    <string>14309</string>
                    <string>14323</string>
                    <string>14325</string>
                    <string>14580</string>
                    <string>14582</string>
                    <string>14585</string>
                    <string>14587</string>
                </array>
                <key>childLinkers</key>
                <array/>
            </dict>
            <dict>
                <key>id</key>
                <string>758</string>
                <key>children</key>
                <array>
                    <string>6686</string>
                    <string>6706</string>
                    <string>6708</string>
                    <string>6710</string>
                    <string>6712</string>
                    <string>6714</string>
                    <string>6716</string>
                    <string>6718</string>
                    <string>6720</string>
                    <string>6726</string>
                    <string>6728</string>
                    <string>6730</string>
                    <string>6732</string>
                    <string>6734</string>
                    <string>6736</string>
                    <string>6738</string>
                    <string>6743</string>
                    <string>6745</string>
                    <string>6747</string>
                    <string>6752</string>
                    <string>6754</string>
                    <string>6772</string>
                    <string>6785</string>
                    <string>7428</string>
                    <string>7831</string>
                    <string>8066</string>
                    <string>8069</string>
                    <string>9123</string>
                    <string>9126</string>
                    <string>13408</string>
                    <string>13416</string>
                    <string>14328</string>
                    <string>14331</string>
                    <string>14341</string>
                    <string>14343</string>
                    <string>14345</string>
                    <string>14347</string>
                    <string>14349</string>
                    <string>14365</string>
                    <string>14367</string>
                    <string>14369</string>
                    <string>14393</string>
                    <string>14398</string>
                </array>
                <key>childLinkers</key>
                <array/>
            </dict>
            <dict>
                <key>id</key>
                <string>959</string>
                <key>children</key>
                <array>
                    <string>6840</string>
                    <string>6892</string>
                    <string>6894</string>
                    <string>6896</string>
                    <string>6898</string>
                    <string>6918</string>
                    <string>6920</string>
                    <string>6922</string>
                    <string>6924</string>
                    <string>6929</string>
                    <string>6932</string>
                    <string>6936</string>
                    <string>6942</string>
                    <string>6947</string>
                    <string>6954</string>
                    <string>6956</string>
                    <string>6958</string>
                    <string>6963</string>
                    <string>6965</string>
                    <string>6975</string>
                    <string>6977</string>
                    <string>6979</string>
                    <string>6981</string>
                    <string>6983</string>
                    <string>6985</string>
                    <string>6988</string>
                    <string>6992</string>
                    <string>7040</string>
                    <string>7042</string>
                    <string>7044</string>
                    <string>7046</string>
                    <string>7054</string>
                    <string>7057</string>
                    <string>7071</string>
                    <string>7307</string>
                    <string>7313</string>
                    <string>7315</string>
                    <string>7317</string>
                    <string>7322</string>
                    <string>7324</string>
                    <string>7326</string>
                    <string>7328</string>
                    <string>7330</string>
                    <string>7332</string>
                    <string>7432</string>
                    <string>14417</string>
                    <string>14420</string>
                    <string>14448</string>
                    <string>14455</string>
                    <string>14457</string>
                    <string>14463</string>
                    <string>14466</string>
                </array>
                <key>childLinkers</key>
                <array/>
            </dict>
            <dict>
                <key>id</key>
                <string>1091</string>
                <key>children</key>
                <array>
                    <string>7119</string>
                    <string>7121</string>
                    <string>7123</string>
                    <string>7125</string>
                    <string>7127</string>
                    <string>7129</string>
                    <string>7131</string>
                    <string>7133</string>
                    <string>7135</string>
                    <string>7137</string>
                    <string>7139</string>
                    <string>7141</string>
                    <string>7143</string>
                    <string>7145</string>
                    <string>7147</string>
                    <string>7149</string>
                    <string>7151</string>
                    <string>7153</string>
                    <string>7158</string>
                    <string>7160</string>
                    <string>7162</string>
                    <string>7169</string>
                    <string>7173</string>
                    <string>7252</string>
                    <string>7254</string>
                    <string>7256</string>
                    <string>7259</string>
                    <string>7261</string>
                    <string>7338</string>
                    <string>7344</string>
                    <string>7346</string>
                    <string>7348</string>
                    <string>7355</string>
                    <string>7357</string>
                    <string>7359</string>
                    <string>7361</string>
                    <string>7363</string>
                    <string>7365</string>
                    <string>7367</string>
                    <string>7398</string>
                    <string>7400</string>
                    <string>7403</string>
                    <string>7405</string>
                    <string>7407</string>
                    <string>7436</string>
                    <string>7440</string>
                    <string>11097</string>
                    <string>13645</string>
                    <string>13647</string>
                    <string>13649</string>
                    <string>13651</string>
                    <string>13806</string>
                    <string>13846</string>
                    <string>13859</string>
                    <string>13861</string>
                    <string>13863</string>
                    <string>13883</string>
                    <string>13885</string>
                    <string>7167</string>
                    <string>13930</string>
                    <string>13937</string>
                    <string>13939</string>
                    <string>13941</string>
                    <string>13943</string>
                    <string>13945</string>
                    <string>13948</string>
                    <string>13962</string>
                    <string>13965</string>
                    <string>13967</string>
                </array>
                <key>childLinkers</key>
                <array/>
            </dict>
            <dict>
                <key>id</key>
                <string>1300</string>
                <key>children</key>
                <array>
                    <string>7486</string>
                    <string>7488</string>
                    <string>7490</string>
                    <string>7492</string>
                    <string>7500</string>
                    <string>7502</string>
                    <string>7504</string>
                    <string>7506</string>
                    <string>7520</string>
                    <string>7839</string>
                    <string>7841</string>
                    <string>7844</string>
                    <string>7849</string>
                    <string>7852</string>
                    <string>7859</string>
                    <string>7863</string>
                    <string>7878</string>
                    <string>7973</string>
                    <string>7975</string>
                    <string>7977</string>
                    <string>7979</string>
                    <string>8025</string>
                    <string>8027</string>
                    <string>8029</string>
                    <string>8031</string>
                    <string>8037</string>
                    <string>8039</string>
                    <string>8041</string>
                    <string>7835</string>
                    <string>10085</string>
                    <string>10089</string>
                    <string>11121</string>
                    <string>11128</string>
                    <string>11130</string>
                    <string>11134</string>
                    <string>11136</string>
                    <string>11176</string>
                    <string>11237</string>
                    <string>11239</string>
                    <string>11241</string>
                    <string>11243</string>
                    <string>11251</string>
                    <string>11253</string>
                    <string>11256</string>
                    <string>11270</string>
                    <string>11334</string>
                    <string>11416</string>
                    <string>11418</string>
                    <string>11431</string>
                    <string>11434</string>
                    <string>11459</string>
                    <string>11461</string>
                    <string>11463</string>
                    <string>12686</string>
                    <string>12688</string>
                    <string>12690</string>
                    <string>12693</string>
                    <string>12695</string>
                    <string>12697</string>
                    <string>14492</string>
                    <string>14494</string>
                    <string>14496</string>
                </array>
                <key>childLinkers</key>
                <array/>
            </dict>
            <dict>
                <key>id</key>
                <string>1463</string>
                <key>children</key>
                <array>
                    <string>8853</string>
                    <string>8855</string>
                    <string>8869</string>
                    <string>8871</string>
                    <string>8873</string>
                    <string>8875</string>
                    <string>8877</string>
                    <string>8881</string>
                    <string>8883</string>
                    <string>8885</string>
                    <string>8887</string>
                    <string>8950</string>
                    <string>8952</string>
                    <string>8984</string>
                    <string>8991</string>
                    <string>9002</string>
                    <string>9008</string>
                    <string>9011</string>
                    <string>9015</string>
                    <string>9023</string>
                    <string>9025</string>
                    <string>9027</string>
                    <string>9029</string>
                    <string>9043</string>
                    <string>9056</string>
                    <string>9090</string>
                    <string>9111</string>
                    <string>10093</string>
                    <string>10097</string>
                    <string>11546</string>
                    <string>11576</string>
                    <string>14504</string>
                    <string>14507</string>
                    <string>14511</string>
                    <string>14514</string>
                    <string>14520</string>
                    <string>14522</string>
                    <string>14524</string>
                    <string>14531</string>
                    <string>14534</string>
                    <string>14537</string>
                    <string>14544</string>
                    <string>14556</string>
                </array>
                <key>childLinkers</key>
                <array/>
            </dict>
            <dict>
                <key>id</key>
                <string>4072</string>
                <key>children</key>
                <array>
                    <string>4214</string>
                    <string>4157</string>
                    <string>4156</string>
                    <string>4091</string>
                    <string>9180</string>
                    <string>9182</string>
                    <string>9208</string>
                    <string>9210</string>
                    <string>9212</string>
                    <string>9214</string>
                    <string>9216</string>
                    <string>9218</string>
                    <string>9220</string>
                    <string>9222</string>
                    <string>9224</string>
                    <string>9226</string>
                    <string>9228</string>
                    <string>9230</string>
                    <string>9232</string>
                    <string>9234</string>
                    <string>9236</string>
                    <string>9238</string>
                    <string>9240</string>
                    <string>9242</string>
                    <string>9244</string>
                    <string>9246</string>
                    <string>9248</string>
                    <string>9250</string>
                    <string>9272</string>
                    <string>9283</string>
                    <string>9285</string>
                    <string>9287</string>
                    <string>9289</string>
                    <string>9291</string>
                    <string>9293</string>
                    <string>9295</string>
                    <string>9297</string>
                    <string>9299</string>
                    <string>9301</string>
                    <string>9303</string>
                    <string>9314</string>
                    <string>9316</string>
                    <string>9318</string>
                    <string>9320</string>
                    <string>9322</string>
                    <string>9324</string>
                    <string>9326</string>
                    <string>9333</string>
                    <string>9335</string>
                    <string>9337</string>
                    <string>9339</string>
                    <string>9341</string>
                    <string>9343</string>
                    <string>9361</string>
                    <string>9365</string>
                    <string>9368</string>
                    <string>9373</string>
                    <string>9383</string>
                    <string>9385</string>
                    <string>9387</string>
                    <string>9389</string>
                    <string>9391</string>
                    <string>9396</string>
                    <string>9398</string>
                    <string>9400</string>
                    <string>9404</string>
                    <string>9406</string>
                    <string>9410</string>
                    <string>9412</string>
                    <string>9415</string>
                    <string>9421</string>
                    <string>9423</string>
                    <string>9425</string>
                    <string>9427</string>
                    <string>9431</string>
                    <string>9433</string>
                    <string>9436</string>
                    <string>9442</string>
                    <string>9444</string>
                    <string>9542</string>
                    <string>9545</string>
                    <string>9548</string>
                    <string>9552</string>
                    <string>9556</string>
                    <string>9800</string>
                    <string>9803</string>
                    <string>9806</string>
                    <string>9809</string>
                    <string>9811</string>
                    <string>9814</string>
                    <string>9817</string>
                    <string>9819</string>
                    <string>9821</string>
                    <string>9826</string>
                    <string>9870</string>
                    <string>9874</string>
                    <string>9877</string>
                    <string>9881</string>
                    <string>9884</string>
                    <string>9887</string>
                    <string>9890</string>
                    <string>9893</string>
                    <string>9896</string>
                    <string>9907</string>
                    <string>9909</string>
                    <string>10101</string>
                    <string>10105</string>
                    <string>11952</string>
                    <string>11987</string>
                    <string>11994</string>
                    <string>11996</string>
                    <string>14598</string>
                    <string>14600</string>
                    <string>14605</string>
                    <string>14608</string>
                    <string>14612</string>
                    <string>14624</string>
                    <string>14630</string>
                    <string>9270</string>
                    <string>14620</string>
                    <string>14637</string>
                    <string>14649</string>
                    <string>14651</string>
                    <string>14653</string>
                    <string>14655</string>
                    <string>14657</string>
                </array>
                <key>childLinkers</key>
                <array/>
            </dict>
            <dict>
                <key>id</key>
                <string>5549</string>
                <key>children</key>
                <array>
                    <string>5680</string>
                    <string>9587</string>
                    <string>9693</string>
                    <string>9695</string>
                    <string>9697</string>
                    <string>9699</string>
                    <string>9701</string>
                    <string>9713</string>
                    <string>9715</string>
                    <string>9717</string>
                    <string>9719</string>
                    <string>9721</string>
                    <string>9723</string>
                    <string>9725</string>
                    <string>9727</string>
                    <string>9729</string>
                    <string>9731</string>
                    <string>9735</string>
                    <string>9737</string>
                    <string>9750</string>
                    <string>9752</string>
                    <string>9754</string>
                    <string>9756</string>
                    <string>9758</string>
                    <string>9760</string>
                    <string>9762</string>
                    <string>9764</string>
                    <string>9766</string>
                    <string>9768</string>
                    <string>9776</string>
                    <string>9778</string>
                    <string>9780</string>
                    <string>9782</string>
                    <string>9784</string>
                    <string>9912</string>
                    <string>9914</string>
                    <string>9916</string>
                    <string>9926</string>
                    <string>9928</string>
                    <string>9930</string>
                    <string>9954</string>
                    <string>9959</string>
                    <string>9961</string>
                    <string>9964</string>
                    <string>9968</string>
                    <string>9971</string>
                    <string>9975</string>
                    <string>9979</string>
                    <string>9986</string>
                    <string>9994</string>
                    <string>9998</string>
                    <string>10000</string>
                    <string>10003</string>
                    <string>10007</string>
                    <string>10010</string>
                    <string>10012</string>
                    <string>10014</string>
                    <string>10016</string>
                    <string>10023</string>
                    <string>10026</string>
                    <string>10029</string>
                    <string>10031</string>
                    <string>10033</string>
                    <string>10035</string>
                    <string>10037</string>
                    <string>10039</string>
                    <string>10041</string>
                    <string>10043</string>
                    <string>10045</string>
                    <string>10048</string>
                    <string>10050</string>
                    <string>10052</string>
                    <string>10054</string>
                    <string>10056</string>
                    <string>10058</string>
                    <string>10060</string>
                    <string>10066</string>
                    <string>10069</string>
                    <string>10072</string>
                    <string>10074</string>
                    <string>10076</string>
                    <string>10078</string>
                    <string>10080</string>
                    <string>10109</string>
                    <string>10113</string>
                    <string>10117</string>
                    <string>12068</string>
                    <string>12253</string>
                    <string>12274</string>
                    <string>12320</string>
                    <string>12337</string>
                    <string>12339</string>
                    <string>12342</string>
                    <string>12387</string>
                    <string>12392</string>
                    <string>12418</string>
                </array>
                <key>childLinkers</key>
                <array/>
            </dict>
        </array>
    </dict>
</plist>
